springform/Forms.py
springform/Model.py
springform/Template.py
springform/__init__.py
springform-0.6.5.dist-info/LICENSE
springform-0.6.5.dist-info/METADATA
springform-0.6.5.dist-info/WHEEL
springform-0.6.5.dist-info/top_level.txt
springform-0.6.5.dist-info/RECORD
