Metadata-Version: 2.1
Name: springform
Version: 0.6.5
Summary: A simple templating system for Python class files.
Home-page: https://github.com/dluman/springform
License: UNKNOWN
Platform: UNKNOWN
